[
  {
    "full_name": "mhutchie/vscode-git-graph",
    "stargazers_count": 1246,
    "open_issues_count": 132,
    "forks_count": 143
  },
  {
    "full_name": "brianc/node-postgres",
    "stargazers_count": 10638,
    "open_issues_count": 389,
    "forks_count": 1123
  },
  {
    "full_name": "antongolub/yarn-audit-fix",
    "stargazers_count": 131,
    "open_issues_count": 11,
    "forks_count": 6
  },
  {
    "full_name": "remix-run/history",
    "stargazers_count": 7902,
    "open_issues_count": 114,
    "forks_count": 992
  },
  {
    "full_name": "open-sauced/open-sauced",
    "stargazers_count": 775,
    "open_issues_count": 19,
    "forks_count": 377
  },
  {
    "full_name": "sindresorhus/emittery",
    "stargazers_count": 1471,
    "open_issues_count": 12,
    "forks_count": 73
  },
  {
    "full_name": "vue-terminal/vue-termui",
    "stargazers_count": 119,
    "open_issues_count": 5,
    "forks_count": 4
  },
  {
    "full_name": "kadirnar/losshub",
    "stargazers_count": 12,
    "open_issues_count": 0,
    "forks_count": 1
  },
  {
    "full_name": "sdv-dev/CTGAN",
    "stargazers_count": 719,
    "open_issues_count": 35,
    "forks_count": 186
  },
  {
    "full_name": "vueup/vue-quill",
    "stargazers_count": 398,
    "open_issues_count": 21,
    "forks_count": 57
  },
  {
    "full_name": "peacecwz/shazam-demo",
    "stargazers_count": 119,
    "open_issues_count": 1,
    "forks_count": 34
  },
  {
    "full_name": "peacecwz/mutty",
    "stargazers_count": 14,
    "open_issues_count": 1,
    "forks_count": 3
  },
  {
    "full_name": "radix-ui/icons",
    "stargazers_count": 1168,
    "open_issues_count": 23,
    "forks_count": 47
  },
  {
    "full_name": "radix-ui/colors",
    "stargazers_count": 603,
    "open_issues_count": 8,
    "forks_count": 18
  },
  {
    "full_name": "radix-ui/design-system",
    "stargazers_count": 1535,
    "open_issues_count": 12,
    "forks_count": 123
  },
  {
    "full_name": "radix-ui/primitives",
    "stargazers_count": 5901,
    "open_issues_count": 127,
    "forks_count": 217
  },
  {
    "full_name": "sd-webui/stable-diffusion-webui",
    "stargazers_count": 2634,
    "open_issues_count": 104,
    "forks_count": 289
  },
  {
    "full_name": "instill-ai/vdp",
    "stargazers_count": 152,
    "open_issues_count": 18,
    "forks_count": 11
  },
  {
    "full_name": "apple/swift-book",
    "stargazers_count": 1155,
    "open_issues_count": 15,
    "forks_count": 41
  },
  {
    "full_name": "akburg/elgatokeylight",
    "stargazers_count": 14,
    "open_issues_count": 1,
    "forks_count": 2
  },
  {
    "full_name": "discord/discord-api-docs",
    "stargazers_count": 4763,
    "open_issues_count": 179,
    "forks_count": 1172
  },
  {
    "full_name": "discord/react-dnd-accessible-backend",
    "stargazers_count": 478,
    "open_issues_count": 3,
    "forks_count": 25
  },
  {
    "full_name": "alyssaxuu/motionity",
    "stargazers_count": 1960,
    "open_issues_count": 6,
    "forks_count": 94
  },
  {
    "full_name": "blade-ui-kit/blade-heroicons",
    "stargazers_count": 342,
    "open_issues_count": 0,
    "forks_count": 36
  },
  {
    "full_name": "mozilla/pontoon",
    "stargazers_count": 1190,
    "open_issues_count": 316,
    "forks_count": 514
  },
  {
    "full_name": "davidphilipbarr/Sweep",
    "stargazers_count": 713,
    "open_issues_count": 1,
    "forks_count": 115
  },
  {
    "full_name": "antfu/icones",
    "stargazers_count": 2497,
    "open_issues_count": 14,
    "forks_count": 122
  },
  {
    "full_name": "xonsh/xonsh",
    "stargazers_count": 6274,
    "open_issues_count": 246,
    "forks_count": 576
  },
  {
    "full_name": "visionmedia/page.js",
    "stargazers_count": 7531,
    "open_issues_count": 126,
    "forks_count": 724
  },
  {
    "full_name": "runsidekick/sidekick",
    "stargazers_count": 1393,
    "open_issues_count": 2,
    "forks_count": 51
  }
]